yaml_config_override/__init__.py
yaml_config_override-0.5.dist-info/LICENSE
yaml_config_override-0.5.dist-info/METADATA
yaml_config_override-0.5.dist-info/WHEEL
yaml_config_override-0.5.dist-info/RECORD
